sequential_functions/__init__.py
sequential_functions/batch.py
sequential_functions/callable.py
sequential_functions/compose.py
sequential_functions/queue_generator_wrapper.py
sequential_functions-0.1.3.dist-info/LICENSE
sequential_functions-0.1.3.dist-info/METADATA
sequential_functions-0.1.3.dist-info/WHEEL
sequential_functions-0.1.3.dist-info/top_level.txt
sequential_functions-0.1.3.dist-info/RECORD
