Metadata-Version: 2.1
Name: sequential-functions
Version: 0.1.3
Summary: Compose functions and sequentially call them. Run sequence in multiple threads or processes!
Author: Thomas Rowntree
Project-URL: Homepage, https://github.com/ChainBreak/sequential_functions
Project-URL: Bug Tracker, https://github.com/ChainBreak/sequential_functions/issues
Classifier: Programming Language :: Python :: 3
Classifier: License :: OSI Approved :: MIT License
Classifier: Operating System :: OS Independent
Requires-Python: >=3.7
License-File: LICENSE
